weirdbb91/__init__.py
weirdbb91/test.py
weirdbb91/utils/__init__.py
weirdbb91/utils/random_address.py
weirdbb91-1.0.0.dist-info/LICENSE
weirdbb91-1.0.0.dist-info/METADATA
weirdbb91-1.0.0.dist-info/WHEEL
weirdbb91-1.0.0.dist-info/top_level.txt
weirdbb91-1.0.0.dist-info/RECORD
