Metadata-Version: 2.1
Name: weirdbb91
Version: 1.0.0
Summary: it's my first pip deploy, say hi and bye
Home-page: https://github.com/weirdbb91/first_pip_deploy
Author: seungho.baek
Author-email: weirdbb91@gmail.com
License: MIT
Download-URL: https://github.com/weirdbb91/first_pip_deploy/archive/master.zip
Keywords: pypi deploy weirdbb91
Platform: UNKNOWN
Classifier: License :: OSI Approved :: MIT License
Classifier: Programming Language :: Python :: 3
Classifier: Operating System :: OS Independent
Requires-Python: >=3
